kmerator/__init__.py
kmerator/config.py
kmerator/ensembl.py
kmerator/ensembl2.py
kmerator/fasta.py
kmerator/info.py
kmerator/kmerator.py
kmerator/kmerize.py
kmerator/kmerize2.py
kmerator/ktools.py
kmerator/sequences.py
kmerator/utils.py
kmerator2-0.6.4b0.dist-info/LICENCE.md
kmerator2-0.6.4b0.dist-info/METADATA
kmerator2-0.6.4b0.dist-info/WHEEL
kmerator2-0.6.4b0.dist-info/entry_points.txt
kmerator2-0.6.4b0.dist-info/top_level.txt
kmerator2-0.6.4b0.dist-info/RECORD
