Metadata-Version: 2.1
Name: kmerator2
Version: 0.6.4b0
Summary: Find specific gene or transcript kmers. And more.
Home-page: UNKNOWN
Author: Sébastien RIQUIER, IRMB, Montpellier
Author-email: sebastien.riquier@ucd.ie
License: GPLv3
Platform: UNKNOWN
Classifier: Development Status :: 3 - Alpha
Classifier: License :: OSI Approved :: GNU General Public License v3 (GPLv3)
Classifier: Operating System :: POSIX :: Linux
Classifier: Programming Language :: Python
Classifier: Natural Language :: English
Classifier: Intended Audience :: Science/Research
Requires-Python: >=3.6
Requires-Dist: PyYAML
Requires-Dist: bs4
